{
  "name": "Weekly Product QA Audit - Example App",
  "schedule": {
    "kind": "cron",
    "expr": "0 9 * * 1",
    "tz": "Asia/Manila"
  },
  "sessionTarget": "isolated",
  "enabled": false,
  "payload": {
    "kind": "agentTurn",
    "message": "Run the `product-qa-audit` skill against Example App at https://example.com. Audit mode: cron full audit. Perform a comprehensive browser-based QA and UX audit. Explore all accessible pages and major user flows, especially sign-up, login, onboarding, dashboard, settings, and the core value-delivery workflow. If authentication is required, register using Lisa's email if no account exists; otherwise log in. Capture screenshots only when they materially improve bug evidence or clarify a confusing visual state. Save all created artifacts into `/home/node/.openclaw/workspace/projects/lisa-hayes-main-folder/` using a dated subfolder and timestamped filenames. Generate a complete System Health & Optimization Report with these sections in order: Executive Summary, Audit Scope, The Bug List (Must Fix), The Enhancement List (Should Improve), Strategic Recommendations, Appendix: Evidence & Notes. If the product is too large to cover fully in one run, state what was covered and what was skipped. If blocked by captcha, email verification, missing seed data, or environment issues, report that clearly instead of guessing.",
    "model": "sonnet",
    "thinking": "low",
    "timeoutSeconds": 1800
  },
  "delivery": {
    "mode": "announce"
  }
}
